README.md
setup.py
CubeJsClient.egg-info/PKG-INFO
CubeJsClient.egg-info/SOURCES.txt
CubeJsClient.egg-info/dependency_links.txt
CubeJsClient.egg-info/requires.txt
CubeJsClient.egg-info/top_level.txt
cube_js_client/__init__.py
cube_js_client/client.py
cube_js_client/exceptions.py
cubejsclient.egg-info/PKG-INFO
cubejsclient.egg-info/SOURCES.txt
cubejsclient.egg-info/dependency_links.txt
cubejsclient.egg-info/requires.txt
cubejsclient.egg-info/top_level.txt