Metadata-Version: 2.1
Name: CubeJsClient
Version: 0.1.1
Summary: Cube.js Client for Python
Home-page: https://github.com/downstreamimpact/CubeJsClient
Author: Matt Ferrante
Author-email: matt@downstreamimpact.com
License: MIT
Platform: UNKNOWN
